crux/__init__.py
crux/__version__.py
crux/_client.py
crux/_compat.py
crux/_config.py
crux/_utils.py
crux/apis.py
crux/exceptions.py
crux/models/__init__.py
crux/models/_factory.py
crux/models/dataset.py
crux/models/delivery.py
crux/models/file.py
crux/models/folder.py
crux/models/identity.py
crux/models/ingestion.py
crux/models/job.py
crux/models/label.py
crux/models/model.py
crux/models/permission.py
crux/models/resource.py
crux-1.4.dist-info/LICENSE
crux-1.4.dist-info/METADATA
crux-1.4.dist-info/WHEEL
crux-1.4.dist-info/top_level.txt
crux-1.4.dist-info/RECORD
