Metadata-Version: 2.1
Name: crux
Version: 1.4
Summary: Crux Informatics API client library
Home-page: https://github.com/cruxinformatics/crux-python
Author: Crux Informatics, Inc.
Author-email: python-opensource@cruxinformatics.com
License: MIT
Keywords: crux-python
Classifier: Development Status :: 3 - Alpha
Classifier: Intended Audience :: Developers
Classifier: Intended Audience :: Science/Research
Classifier: License :: OSI Approved :: MIT License
Classifier: Operating System :: OS Independent
Classifier: Programming Language :: Python
Classifier: Programming Language :: Python :: 2
Classifier: Programming Language :: Python :: 2.7
Classifier: Programming Language :: Python :: 3
Classifier: Programming Language :: Python :: 3.5
Classifier: Programming Language :: Python :: 3.6
Classifier: Programming Language :: Python :: 3.7
Classifier: Topic :: Software Development
Requires-Python: >=2.7, !=3.0.*, !=3.1.*, !=3.2.*, !=3.3.*, !=3.4.*
License-File: LICENSE
Requires-Dist: google-resumable-media[requests]
Requires-Dist: python-dateutil
Requires-Dist: enum34; python_version < "3.4"
Requires-Dist: typing; python_version < "3.5"
